LICENSE
MANIFEST.in
README.md
pyproject.toml
setup.py
python/dectris/__init__.py
python/dectris/compression.c
python/dectris_compression.egg-info/PKG-INFO
python/dectris_compression.egg-info/SOURCES.txt
python/dectris_compression.egg-info/dependency_links.txt
python/dectris_compression.egg-info/top_level.txt
src/compression.c
src/compression.h
third_party/bitshuffle/LICENSE-APACHE
third_party/bitshuffle/LICENSE-MIT
third_party/bitshuffle/src/bitshuffle.c
third_party/bitshuffle/src/bitshuffle.h
third_party/lz4/LICENSE
third_party/lz4/lib/lz4.c
third_party/lz4/lib/lz4.h